domacc/__init__.py
domacc/accounting.py
domacc/accountingData.py
domacc/budget.py
domacc/fileReader.py
domacc-0.1.dist-info/METADATA
domacc-0.1.dist-info/WHEEL
domacc-0.1.dist-info/top_level.txt
domacc-0.1.dist-info/RECORD
